[
    {
        "count": 372,
        "dist": 0.0688634,
        "tiles": "SMRT-Bell[1-43](f)"
    },
    {
        "count": 156,
        "dist": 0.0288782,
        "tiles": "SMRT-Bell[1-41](f)"
    },
    {
        "count": 137,
        "dist": 0.0253610,
        "tiles": "SMRT-Bell[1-33](f)"
    },
    {
        "count": 83,
        "dist": 0.0153647,
        "tiles": "SMRT-Bell[1-43](f),Payload[2182-2193](t)"
    },
    {
        "count": 77,
        "dist": 0.0142540,
        "tiles": "SMRT-Bell[1-43](f),Payload[2182-2194](t)"
    },
    {
        "count": 75,
        "dist": 0.0138837,
        "tiles": "SMRT-Bell[1-43](f),Payload[2182-2195](t)"
    },
    {
        "count": 75,
        "dist": 0.0138837,
        "tiles": "SMRT-Bell[3-33](f)"
    },
    {
        "count": 74,
        "dist": 0.0136986,
        "tiles": "Payload[2796-2806](t),SMRT-Bell[1-43](f)"
    },
    {
        "count": 69,
        "dist": 0.0127730,
        "tiles": "SMRT-Bell[3-43](f)"
    },
    {
        "count": 63,
        "dist": 0.0116623,
        "tiles": "Payload[2796-2806](t),SMRT-Bell[1-41](f)"
    },
    {
        "count": 46,
        "dist": 0.0085154,
        "tiles": "Payload[2182-2195](t),SMRT-Bell[1-43](f),Payload[2182-2194](t)"
    },
    {
        "count": 41,
        "dist": 0.0075898,
        "tiles": "SMRT-Bell[1-34](f)"
    },
    {
        "count": 41,
        "dist": 0.0075898,
        "tiles": "SMRT-Bell[14-43](f)"
    },
    {
        "count": 36,
        "dist": 0.0066642,
        "tiles": "SMRT-Bell[3-41](f)"
    },
    {
        "count": 34,
        "dist": 0.0062940,
        "tiles": "SMRT-Bell[16-43](f)"
    },
    {
        "count": 30,
        "dist": 0.0055535,
        "tiles": "SMRT-Bell[1-41](f),Payload[2182-2195](t)"
    },
    {
        "count": 29,
        "dist": 0.0053684,
        "tiles": "SMRT-Bell[1-43](t)"
    },
    {
        "count": 27,
        "dist": 0.0049981,
        "tiles": "Payload[2796-2806](t),SMRT-Bell[1-33](f)"
    },
    {
        "count": 26,
        "dist": 0.0048130,
        "tiles": "SMRT-Bell[1-33](f),Payload[2182-2194](t)"
    },
    {
        "count": 25,
        "dist": 0.0046279,
        "tiles": "Payload[2182-2195](t),SMRT-Bell[1-43](f),Payload[2182-2193](t)"
    },
    {
        "count": 25,
        "dist": 0.0046279,
        "tiles": "SMRT-Bell[1-31](f)"
    },
    {
        "count": 25,
        "dist": 0.0046279,
        "tiles": "SMRT-Bell[1-41](f),Payload[2182-2194](t)"
    },
    {
        "count": 24,
        "dist": 0.0044428,
        "tiles": "SMRT-Bell[1-33](f),Payload[2182-2193](t)"
    },
    {
        "count": 24,
        "dist": 0.0044428,
        "tiles": "SMRT-Bell[1-41](f),Payload[2182-2193](t)"
    },
    {
        "count": 24,
        "dist": 0.0044428,
        "tiles": "SMRT-Bell[27-43](f),SMRT-Bell[1-33](f)"
    },
    {
        "count": 23,
        "dist": 0.0042577,
        "tiles": "Payload[2796-2806](t),SMRT-Bell[1-34](f)"
    },
    {
        "count": 22,
        "dist": 0.0040726,
        "tiles": "SMRT-Bell[1-22](f)"
    },
    {
        "count": 22,
        "dist": 0.0040726,
        "tiles": "SMRT-Bell[1-43](f),Payload[2796-2806](f)"
    },
    {
        "count": 21,
        "dist": 0.0038874,
        "tiles": "SMRT-Bell[27-41](f),SMRT-Bell[5-33](f)"
    },
    {
        "count": 20,
        "dist": 0.0037023,
        "tiles": "SMRT-Bell[1-28](f)"
    },
    {
        "count": 20,
        "dist": 0.0037023,
        "tiles": "SMRT-Bell[10-43](f)"
    },
    {
        "count": 20,
        "dist": 0.0037023,
        "tiles": "SMRT-Bell[3-43](f),Payload[2182-2194](t)"
    },
    {
        "count": 19,
        "dist": 0.0035172,
        "tiles": "SMRT-Bell[27-43](f),SMRT-Bell[5-33](f)"
    },
    {
        "count": 18,
        "dist": 0.0033321,
        "tiles": "Payload[2182-2195](t),SMRT-Bell[1-43](f)"
    },
    {
        "count": 17,
        "dist": 0.0031470,
        "tiles": "SMRT-Bell[1-43](f),Payload[2182-2192](t)"
    },
    {
        "count": 17,
        "dist": 0.0031470,
        "tiles": "SMRT-Bell[3-43](f),Payload[2182-2195](t)"
    },
    {
        "count": 16,
        "dist": 0.0029619,
        "tiles": "SMRT-Bell[1-33](f),Payload[2182-2195](t)"
    },
    {
        "count": 16,
        "dist": 0.0029619,
        "tiles": "SMRT-Bell[1-43](f),Payload[2796-2806](f),Payload[2182-2193](t)"
    },
    {
        "count": 16,
        "dist": 0.0029619,
        "tiles": "SMRT-Bell[1-43](f),Payload[2796-2806](f),Payload[2182-2194](t)"
    },
    {
        "count": 16,
        "dist": 0.0029619,
        "tiles": "SMRT-Bell[3-34](f)"
    },
    {
        "count": 15,
        "dist": 0.0027767,
        "tiles": "Payload[2796-2806](t),SMRT-Bell[3-41](f)"
    },
    {
        "count": 15,
        "dist": 0.0027767,
        "tiles": "SMRT-Bell[1-34](f),Payload[2182-2194](t)"
    },
    {
        "count": 15,
        "dist": 0.0027767,
        "tiles": "SMRT-Bell[10-33](f)"
    },
    {
        "count": 15,
        "dist": 0.0027767,
        "tiles": "SMRT-Bell[17-43](f)"
    },
    {
        "count": 14,
        "dist": 0.0025916,
        "tiles": "SMRT-Bell[1-33](f),Payload[2796-2806](f)"
    },
    {
        "count": 14,
        "dist": 0.0025916,
        "tiles": "SMRT-Bell[1-41](f),Payload[2796-2806](f)"
    },
    {
        "count": 14,
        "dist": 0.0025916,
        "tiles": "SMRT-Bell[1-43](f),Payload[2183-2194](t)"
    },
    {
        "count": 14,
        "dist": 0.0025916,
        "tiles": "SMRT-Bell[15-43](f)"
    },
    {
        "count": 14,
        "dist": 0.0025916,
        "tiles": "SMRT-Bell[6-19](t),Payload[2182-2195](t),SMRT-Bell[6-43](f)"
    },
    {
        "count": 13,
        "dist": 0.0024065,
        "tiles": "Payload[2796-2806](t),SMRT-Bell[3-33](f)"
    },
    {
        "count": 13,
        "dist": 0.0024065,
        "tiles": "SMRT-Bell[1-32](f)"
    },
    {
        "count": 13,
        "dist": 0.0024065,
        "tiles": "SMRT-Bell[1-43](t),Payload[2182-2195](f)"
    },
    {
        "count": 13,
        "dist": 0.0024065,
        "tiles": "SMRT-Bell[27-41](f),SMRT-Bell[1-20](f)"
    },
    {
        "count": 13,
        "dist": 0.0024065,
        "tiles": "SMRT-Bell[3-31](f)"
    },
    {
        "count": 13,
        "dist": 0.0024065,
        "tiles": "SMRT-Bell[8-23](t),SMRT-Bell[8-43](f)"
    },
    {
        "count": 12,
        "dist": 0.0022214,
        "tiles": "Payload[2182-2195](t),SMRT-Bell[11-43](f)"
    },
    {
        "count": 12,
        "dist": 0.0022214,
        "tiles": "Payload[2182-2195](t),SMRT-Bell[13-43](f)"
    },
    {
        "count": 12,
        "dist": 0.0022214,
        "tiles": "Payload[2796-2806](t),SMRT-Bell[3-34](f)"
    },
    {
        "count": 12,
        "dist": 0.0022214,
        "tiles": "SMRT-Bell[1-33](f),Payload[2796-2806](f),Payload[2182-2194](t)"
    },
    {
        "count": 12,
        "dist": 0.0022214,
        "tiles": "SMRT-Bell[3-33](f),Payload[2182-2194](t)"
    },
    {
        "count": 11,
        "dist": 0.0020363,
        "tiles": "SMRT-Bell[1-33](f),Payload[2796-2806](f),Payload[2182-2195](t)"
    },
    {
        "count": 11,
        "dist": 0.0020363,
        "tiles": "SMRT-Bell[23-43](f)"
    },
    {
        "count": 11,
        "dist": 0.0020363,
        "tiles": "SMRT-Bell[3-28](f)"
    },
    {
        "count": 11,
        "dist": 0.0020363,
        "tiles": "SMRT-Bell[3-33](f),Payload[2796-2806](f)"
    },
    {
        "count": 11,
        "dist": 0.0020363,
        "tiles": "SMRT-Bell[3-41](f),Payload[2182-2194](t)"
    },
    {
        "count": 11,
        "dist": 0.0020363,
        "tiles": "SMRT-Bell[3-43](f),Payload[2182-2193](t)"
    },
    {
        "count": 11,
        "dist": 0.0020363,
        "tiles": "SMRT-Bell[5-41](f)"
    },
    {
        "count": 11,
        "dist": 0.0020363,
        "tiles": "SMRT-Bell[5-43](f)"
    },
    {
        "count": 10,
        "dist": 0.0018512,
        "tiles": "Payload[2182-2195](t),SMRT-Bell[10-43](f)"
    },
    {
        "count": 10,
        "dist": 0.0018512,
        "tiles": "Payload[2796-2806](t),SMRT-Bell[3-43](f)"
    },
    {
        "count": 10,
        "dist": 0.0018512,
        "tiles": "SMRT-Bell[1-19](f)"
    },
    {
        "count": 10,
        "dist": 0.0018512,
        "tiles": "SMRT-Bell[1-28](f),Payload[2182-2194](t)"
    },
    {
        "count": 10,
        "dist": 0.0018512,
        "tiles": "SMRT-Bell[1-28](f),Payload[2182-2195](t)"
    },
    {
        "count": 10,
        "dist": 0.0018512,
        "tiles": "SMRT-Bell[1-33](f),Payload[2796-2806](f),Payload[2182-2193](t)"
    },
    {
        "count": 10,
        "dist": 0.0018512,
        "tiles": "SMRT-Bell[1-41](f),Payload[2796-2806](f),Payload[2182-2194](t)"
    },
    {
        "count": 10,
        "dist": 0.0018512,
        "tiles": "SMRT-Bell[1-43](f),Payload[2183-2193](t)"
    },
    {
        "count": 10,
        "dist": 0.0018512,
        "tiles": "SMRT-Bell[1-43](f),Payload[2183-2195](t)"
    },
    {
        "count": 10,
        "dist": 0.0018512,
        "tiles": "SMRT-Bell[12-23](t),SMRT-Bell[12-43](f)"
    },
    {
        "count": 10,
        "dist": 0.0018512,
        "tiles": "SMRT-Bell[13-23](t),SMRT-Bell[13-43](f)"
    }
]